gpapi2/__init__.py
gpapi2/config.py
gpapi2/device.properties
gpapi2/googleplay.py
gpapi2/googleplay_pb2.py
gpapi2/utils.py
gpapi2-0.4.5.dist-info/LICENSE.md
gpapi2-0.4.5.dist-info/METADATA
gpapi2-0.4.5.dist-info/WHEEL
gpapi2-0.4.5.dist-info/top_level.txt
gpapi2-0.4.5.dist-info/RECORD
