Metadata-Version: 2.1
Name: gpapi2
Version: 0.4.5
Summary: Unofficial python api for google play
Home-page: https://github.com/besendorf/googleplay-api
Author: besendorf
Author-email: janik@besendorf.org
License: GPL3
Platform: UNKNOWN
License-File: LICENSE.md
Requires-Dist: cryptography (>=2.2)
Requires-Dist: protobuf (>=3.5.2)
Requires-Dist: requests
